<?xml version="1.0" encoding="UTF-8" ?>
<!DOCTYPE mapper PUBLIC "-//mybatis.org//DTD Mapper 3.0//EN" "http://mybatis.org/dtd/mybatis-3-mapper.dtd" >
<mapper namespace="jp.co.vermore.mapper.StockMapper" >
  <resultMap id="StockResult" type="jp.co.vermore.entity.Stock" >
    <!--
      WARNING - @mbggenerated
      This element is automatically generated by MyBatis Generator, do not modify.
      This element was generated on Tue Mar 06 15:38:18 CST 2018.
    -->
    <id column="id" property="id" jdbcType="INTEGER" />
    <result column="goods_id" property="goodsId" jdbcType="INTEGER" />
    <result column="size" property="size" jdbcType="TINYINT" />
    <result column="colors" property="colors" jdbcType="TINYINT" />
    <result column="amount" property="amount" jdbcType="INTEGER" />
    <result column="stock" property="stock" jdbcType="INTEGER" />
    <result column="stock_type" property="stockType" jdbcType="TINYINT" />
    <result column="create_datetime" property="createDatetime" jdbcType="TIMESTAMP" />
    <result column="update_datetime" property="updateDatetime" jdbcType="TIMESTAMP" />
    <result column="del_flg" property="delFlg" jdbcType="BIT" />
    <result column="note" property="note" jdbcType="VARCHAR" />
  </resultMap>

  <select id="getAmount" resultMap="StockResult">
    select
    amount,
    colors,
    size
    from
    stock
    where del_flg = 0
    and goods_id = #{goodsId}
    and size = #{size}
    and colors = #{colors}
    order by create_datetime desc
    LIMIT 1
  </select>

  <select id="getColors" resultMap="StockResult">
    select
    distinct colors
    from
    stock
    where del_flg = 0
    and goods_id = #{goodsId}
  </select>

  <select id="getSize" resultMap="StockResult">
    select
    distinct size
    from
    stock
    where del_flg = 0
    and goods_id = #{goodsId}
  </select>

  <insert id="insertStock" parameterType="jp.co.vermore.entity.Stock" >
    insert into stock
    <trim prefix="(" suffix=")" suffixOverrides="," >
      <if test="id != null" >
        id,
      </if>
      <if test="goodsId != null" >
        goods_id,
      </if>
      <if test="size != null" >
        size,
      </if>
      <if test="colors != null" >
        colors,
      </if>
      <if test="amount != null" >
        amount,
      </if>
      <if test="stock != null" >
        stock,
      </if>
      <if test="stockType != null" >
        stock_type,
      </if>
      <if test="createDatetime != null" >
        create_datetime,
      </if>
      <if test="updateDatetime != null" >
        update_datetime,
      </if>
      <if test="delFlg != null" >
        del_flg,
      </if>
      <if test="note != null" >
        note,
      </if>
    </trim>
    <trim prefix="values (" suffix=")" suffixOverrides="," >
      <if test="id != null" >
        #{id,jdbcType=INTEGER},
      </if>
      <if test="goodsId != null" >
        #{goodsId,jdbcType=INTEGER},
      </if>
      <if test="size != null" >
        #{size,jdbcType=TINYINT},
      </if>
      <if test="colors != null" >
        #{colors,jdbcType=TINYINT},
      </if>
      <if test="amount != null" >
        #{amount,jdbcType=INTEGER},
      </if>
      <if test="stock != null" >
        #{stock,jdbcType=INTEGER},
      </if>
      <if test="stockType != null" >
        #{stockType,jdbcType=TINYINT},
      </if>
      <if test="createDatetime != null" >
        #{createDatetime,jdbcType=TIMESTAMP},
      </if>
      <if test="updateDatetime != null" >
        #{updateDatetime,jdbcType=TIMESTAMP},
      </if>
      <if test="delFlg != null" >
        #{delFlg,jdbcType=BIT},
      </if>
      <if test="note != null" >
        #{note,jdbcType=VARCHAR},
      </if>
    </trim>
  </insert>

</mapper>